manga/__init__.py
manga/py.typed
manga/sites/__init__.py
manga/sites/domains.py
manga/sites/test.py
manga/sites/unknown_domain.py
manga/tools/__init__.py
manga/tools/guess.py
manga/tools/inc_chapter.py
manga/tools/no_unicode.py
manga/tools/unnumbered_helper.py
manga/tools/up_number.py
manga/tools/open_new/__init__.py
manga/tools/open_new/cli.py
manga/tools/open_new/open_new.py
manga/tools/open_new/results.py
manga/tools/open_new/tested.py
manga/tools/open_new/thread_handler.py
manga/tools/test_sites/__init__.py
manga/tools/test_sites/cli.py
manga/tools/test_sites/dispatch.py
manga/tools/test_sites/results.py
manga/tools/test_sites/state.py
manga/tools/test_sites/status.py
manga/tools/test_sites/test_sites.py
manga/tools/test_sites/test_url.py
manga/utils/__init__.py
manga/utils/extract_url.py
manga/utils/files.py
manga/utils/log.py
manga/utils/redirect_print_to_tqdm.py
manga/utils/split_on_num.py
manga_scrape-5.16.0.dist-info/licenses/LICENSE
manga_scrape-5.16.0.dist-info/METADATA
manga_scrape-5.16.0.dist-info/WHEEL
manga_scrape-5.16.0.dist-info/entry_points.txt
manga_scrape-5.16.0.dist-info/top_level.txt
manga_scrape-5.16.0.dist-info/RECORD
